uad_shared/__init__.py
uad_shared/core/__init__.py
uad_shared/core/database.py
uad_shared/core/database_artwork.py
uad_shared/enums/__init__.py
uad_shared/enums/common_enums.py
uad_shared/enums/event_enums.py
uad_shared/enums/user_enums.py
uad_shared/models/__init__.py
uad_shared/models/artwork_models.py
uad_shared/models/event_models.py
uad_shared/models/user_models.py
uad_shared/models/user_preference_models.py
uad_shared-0.1.0.dist-info/METADATA
uad_shared-0.1.0.dist-info/WHEEL
uad_shared-0.1.0.dist-info/top_level.txt
uad_shared-0.1.0.dist-info/RECORD
