Metadata-Version: 2.4
Name: uad-shared
Version: 0.1.0
Summary: Shared UAD models, enums, and core database utilities
Requires-Python: >=3.10
Requires-Dist: sqlalchemy>=2.0.0
Requires-Dist: psycopg2-binary>=2.9.0
Dynamic: requires-python
